jupyterbook_patches/__init__.py
jupyterbook_patches/_version.py
jupyterbook_patches/utils.py
jupyterbook_patches/patches/__init__.py
jupyterbook_patches/patches/button.py
jupyterbook_patches/patches/download_patch.py
jupyterbook_patches/patches/fix_hash_jump.py
jupyterbook_patches/patches/layout.py
jupyterbook_patches/patches/margin_patch.py
jupyterbook_patches/patches/mathjax_patch.py
jupyterbook_patches/patches/mystnb_patch.py
jupyterbook_patches/patches/preserve_dropdown_state.py
jupyterbook_patches/patches/_static/download_patch.js
jupyterbook_patches/patches/_static/fix_admonition_style.css
jupyterbook_patches/patches/_static/fix_align_code.css
jupyterbook_patches/patches/_static/fix_align_text_captions.css
jupyterbook_patches/patches/_static/fix_code_header_style.css
jupyterbook_patches/patches/_static/fix_dropdown_style.css
jupyterbook_patches/patches/_static/fix_hash_jump.js
jupyterbook_patches/patches/_static/fix_margin.css
jupyterbook_patches/patches/_static/fix_sidebar_scroll.css
jupyterbook_patches/patches/_static/margin_patch.css
jupyterbook_patches/patches/_static/mathjax_patch.css
jupyterbook_patches/patches/_static/mathjax_patch.js
jupyterbook_patches/patches/_static/preserve_dropdown_state.js
jupyterbook_patches-1.13.1.dist-info/METADATA
jupyterbook_patches-1.13.1.dist-info/WHEEL
jupyterbook_patches-1.13.1.dist-info/licenses/LICENSE
jupyterbook_patches-1.13.1.dist-info/RECORD
