Metadata-Version: 2.4
Name: jupyterbook_patches
Version: 1.13.1
Summary: A collection of useful Jupyter Book v1 patches.
Author-email: rstular <r.stular@student.tudelft.nl>
License-File: LICENSE
Requires-Python: >=3.9
Requires-Dist: sphinx
